umnetdb_utils/__init__.py
umnetdb_utils/base.py
umnetdb_utils/cli.py
umnetdb_utils/umnetdb.py
umnetdb_utils/umnetdisco.py
umnetdb_utils/umnetequip.py
umnetdb_utils/umnetinfo.py
umnetdb_utils/utils.py
umnetdb_utils-0.2.0.dist-info/METADATA
umnetdb_utils-0.2.0.dist-info/WHEEL
umnetdb_utils-0.2.0.dist-info/entry_points.txt
umnetdb_utils-0.2.0.dist-info/RECORD
